aspy21/__init__.py
aspy21/_version.py
aspy21/cache.py
aspy21/client.py
aspy21/models.py
aspy21/query_builder.py
aspy21/utils.py
aspy21/readers/__init__.py
aspy21/readers/aggregates_reader.py
aspy21/readers/base_reader.py
aspy21/readers/formatter.py
aspy21/readers/response_parser.py
aspy21/readers/snapshot_reader.py
aspy21/readers/sql_history_reader.py
aspy21-0.0.4.dist-info/licenses/LICENSE
aspy21-0.0.4.dist-info/METADATA
aspy21-0.0.4.dist-info/WHEEL
aspy21-0.0.4.dist-info/top_level.txt
aspy21-0.0.4.dist-info/RECORD
