Metadata-Version: 2.4
Name: aspy21
Version: 0.0.4
Summary: Modern Python client for Aspen InfoPlus.21 (IP.21) with pandas DataFrame output, tag search, and automatic retry logic
Author: bazdalaz
Maintainer-email: bazdalaz <bazdalaz@users.noreply.github.com>
License-Expression: MIT
Project-URL: Homepage, https://github.com/bazdalaz/aspy21
Project-URL: Repository, https://github.com/bazdalaz/aspy21
Project-URL: Issues, https://github.com/bazdalaz/aspy21/issues
Keywords: aspen,ip21,historian,process data,industrial,ot,scada,aspentech
Classifier: Development Status :: 5 - Production/Stable
Classifier: Intended Audience :: Developers
Classifier: Intended Audience :: Manufacturing
Classifier: Intended Audience :: Science/Research
Classifier: Topic :: Scientific/Engineering
Classifier: Topic :: Software Development :: Libraries :: Python Modules
Classifier: Topic :: System :: Monitoring
Classifier: Programming Language :: Python :: 3
Classifier: Programming Language :: Python :: 3.9
Classifier: Programming Language :: Python :: 3.10
Classifier: Programming Language :: Python :: 3.11
Classifier: Programming Language :: Python :: 3.12
Classifier: Programming Language :: Python :: 3.13
Classifier: Operating System :: OS Independent
Classifier: Typing :: Typed
Requires-Python: >=3.9
License-File: LICENSE
Requires-Dist: httpx>=0.27
Requires-Dist: pandas>=2.0
Requires-Dist: tenacity>=9.0
Provides-Extra: dev
Requires-Dist: pytest>=8.2; extra == "dev"
Requires-Dist: pytest-cov>=5.0; extra == "dev"
Requires-Dist: pytest-asyncio>=0.23; extra == "dev"
Requires-Dist: pytest-benchmark>=5.0; extra == "dev"
Requires-Dist: respx>=0.21; extra == "dev"
Requires-Dist: ruff>=0.8; extra == "dev"
Requires-Dist: pyright>=1.1.389; extra == "dev"
Requires-Dist: types-python-dateutil; extra == "dev"
Requires-Dist: pre-commit>=3.5; extra == "dev"
Requires-Dist: build>=1.0; extra == "dev"
Requires-Dist: twine>=5.0; extra == "dev"
Requires-Dist: setuptools-scm>=8; extra == "dev"
Requires-Dist: python-dotenv>=1.0; extra == "dev"
Provides-Extra: examples
Requires-Dist: python-dotenv>=1.0; extra == "examples"
Dynamic: license-file
